README.txt
bqlib.py
setup.py
bqlib.egg-info/PKG-INFO
bqlib.egg-info/SOURCES.txt
bqlib.egg-info/dependency_links.txt
bqlib.egg-info/requires.txt
bqlib.egg-info/top_level.txt