Metadata-Version: 1.0
Name: bqlib
Version: 0.0.1
Summary: BigQuery python library
Home-page: https://github.com/addsict/bqlib
Author: Yuuki Furuyama
Author-email: addsict@gmail.com
License: MIT
Download-URL: https://github.com/addsict/bqlib/tarball/master
Keywords: google bigquery python library bqlib query
Platform: UNKNOWN
